examples/__init__.py
examples/flaskr.py
examples/hello_world.py
examples/routes.py
examples/static/__init__.py
examples/tests/__init__.py
minion/__init__.py
minion/_version.py
minion/assets.py
minion/core.py
minion/deferred.py
minion/http.py
minion/renderers.py
minion/request.py
minion/routing.py
minion/sessions.py
minion/traversal.py
minion/twisted.py
minion/wsgi.py
minion/tests/__init__.py
minion/tests/test_assets.py
minion/tests/test_core.py
minion/tests/test_deferred.py
minion/tests/test_http.py
minion/tests/test_integration.py
minion/tests/test_renderers.py
minion/tests/test_request.py
minion/tests/test_routing.py
minion/tests/test_sessions.py
minion/tests/test_traversal.py
minion/tests/test_twisted.py
minion/tests/test_utils.py
minion/tests/test_wsgi.py
minion/tests/utils.py
minion-0.24.0.dist-info/DESCRIPTION.rst
minion-0.24.0.dist-info/METADATA
minion-0.24.0.dist-info/RECORD
minion-0.24.0.dist-info/WHEEL
minion-0.24.0.dist-info/metadata.json
minion-0.24.0.dist-info/top_level.txt
