Metadata-Version: 2.0
Name: minion
Version: 0.24.0
Summary: A microframework based on evil intentions and whatever else you've got
Home-page: https://github.com/Julian/Minion
Author: Julian Berman
Author-email: Julian@GrayVines.com
License: MIT
Platform: UNKNOWN
Classifier: Development Status :: 3 - Alpha
Classifier: License :: OSI Approved :: MIT License
Classifier: Operating System :: OS Independent
Classifier: Programming Language :: Python
Classifier: Programming Language :: Python :: 2.7
Classifier: Programming Language :: Python :: 3.4
Classifier: Programming Language :: Python :: 2
Classifier: Programming Language :: Python :: 3
Classifier: Programming Language :: Python :: Implementation :: CPython
Classifier: Programming Language :: Python :: Implementation :: PyPy
Requires-Dist: attrs
Requires-Dist: cached-property
Requires-Dist: future
Requires-Dist: itsdangerous
Requires-Dist: pyrsistent
Requires-Dist: Werkzeug
